django_cbrf/__init__.py
django_cbrf/abstract_models.py
django_cbrf/apps.py
django_cbrf/models.py
django_cbrf/settings.py
django_cbrf/utils.py
django_cbrf/management/__init__.py
django_cbrf/management/commands/__init__.py
django_cbrf/management/commands/load_currencies.py
django_cbrf/management/commands/load_rates.py
django_cbrf/migrations/0001_initial.py
django_cbrf/migrations/0002_denomination_integer.py
django_cbrf/migrations/__init__.py
django_cbrf-1.0.2.dist-info/LICENSE
django_cbrf-1.0.2.dist-info/METADATA
django_cbrf-1.0.2.dist-info/WHEEL
django_cbrf-1.0.2.dist-info/top_level.txt
django_cbrf-1.0.2.dist-info/RECORD
