Metadata-Version: 2.1
Name: django_cbrf
Version: 1.0.2
Summary: Django app to integrate Wrapper for The Central Bank of the Russian Federation site API with your project
Home-page: https://github.com/Egregors/django-cbrf
Author: Vadim Iskuchekov (@egregors)
Author-email: egregors@pm.me
License: MIT
Classifier: Development Status :: 5 - Production/Stable
Classifier: Environment :: Web Environment
Classifier: Intended Audience :: Developers
Classifier: License :: OSI Approved :: BSD License
Classifier: Operating System :: OS Independent
Classifier: Programming Language :: Python
Classifier: Programming Language :: Python :: 3.8
License-File: LICENSE
Requires-Dist: django >=3.1
Requires-Dist: cbrf ==1.0.0
